secrecy/__init__.py
secrecy/main.py
secrecy-0.1.0.dev7.dist-info/METADATA
secrecy-0.1.0.dev7.dist-info/WHEEL
secrecy-0.1.0.dev7.dist-info/entry_points.txt
secrecy-0.1.0.dev7.dist-info/licenses/LICENSE
secrecy-0.1.0.dev7.dist-info/RECORD
