Metadata-Version: 2.4
Name: secrecy
Version: 0.1.0.dev7
Summary: A symmetric encryption utility.
License-File: LICENSE
Requires-Python: >=3.10
Requires-Dist: click>=8.2.0
Requires-Dist: cryptography>=44.0.3
Requires-Dist: platformdirs>=4.4.0
Requires-Dist: python-dotenv>=1.1.0
